{
  "book": "lamentations",
  "chapter": 2,
  "stage_index": 799,
  "verses": [
    {
      "verse": 1,
      "words": [
        {
          "id": "איכה",
          "sbl": "'ei.Khah",
          "gloss": "how!",
          "lemma_strongs": "H0349"
        },
        {
          "id": "יעיב",
          "sbl": "ya.'Iv",
          "gloss": "covers with a cloud(m)",
          "lemma_strongs": "H5743"
        },
        {
          "id": "באפו",
          "sbl": "be.'a.Po",
          "gloss": "his in anger",
          "prefix_strongs": "H9003",
          "lemma_strongs": "H0639",
          "suffix_strongs": "H9023"
        },
        {
          "id": "אדני",
          "sbl": "'a.do.Nai",
          "gloss": "[the] Lord",
          "lemma_strongs": "H0136"
        },
        {
          "id": "את",
          "sbl": "'et-",
          "gloss": "[obj]",
          "lemma_strongs": "H0853"
        },
        {
          "id": "בת",
          "sbl": "bat-",
          "gloss": "[the] daughter of",
          "lemma_strongs": "H1323"
        },
        {
          "id": "ציון",
          "sbl": "tzi.Yon",
          "gloss": "Zion",
          "lemma_strongs": "H6726"
        },
        {
          "id": "השליך",
          "sbl": "hish.Likh",
          "gloss": "has thrown(m)",
          "lemma_strongs": "H7993"
        },
        {
          "id": "משמים",
          "sbl": "mi.sha.Ma.yim",
          "gloss": "from heaven",
          "prefix_strongs": "H9006",
          "lemma_strongs": "H8064"
        },
        {
          "id": "ארץ",
          "sbl": "'E.retz",
          "gloss": "earth",
          "lemma_strongs": "H0776"
        },
        {
          "id": "תפארת",
          "sbl": "tif.'E.ret",
          "gloss": "[the] splendor of",
          "lemma_strongs": "H8597"
        },
        {
          "id": "ישראל",
          "sbl": "Yis.ra.'El",
          "gloss": "Israel",
          "lemma_strongs": "H3478"
        },
        {
          "id": "ולא",
          "sbl": "ve.lo'-",
          "gloss": "and not",
          "prefix_strongs": "H9002",
          "lemma_strongs": "H3808"
        },
        {
          "id": "זכר",
          "sbl": "za.Khar",
          "gloss": "has remembered(m)",
          "lemma_strongs": "H2142"
        },
        {
          "id": "הדם",
          "sbl": "ha.dom-",
          "gloss": "[the] footstool of",
          "lemma_strongs": "H1916"
        },
        {
          "id": "רגליו",
          "sbl": "rag.Lav",
          "gloss": "his feet",
          "lemma_strongs": "H7272",
          "suffix_strongs": "H9023"
        },
        {
          "id": "ביום",
          "sbl": "be.Yom",
          "gloss": "in [the] day of",
          "prefix_strongs": "H9003",
          "lemma_strongs": "H3117"
        },
        {
          "id": "אפו",
          "sbl": "'a.Po",
          "gloss": "his anger",
          "lemma_strongs": "H0639",
          "suffix_strongs": "H9023"
        }
      ],
      "insights": []
    },
    {
      "verse": 2,
      "words": [
        {
          "id": "בלע",
          "sbl": "bi.La'",
          "gloss": "has swallowed up(m)",
          "lemma_strongs": "H1104"
        },
        {
          "id": "אדני",
          "sbl": "'a.do.Nai",
          "gloss": "[the] Lord",
          "lemma_strongs": "H0136"
        },
        {
          "id": "לא",
          "sbl": "lo'",
          "gloss": "and not",
          "prefix_strongs": "H9002",
          "lemma_strongs": "H3808"
        },
        {
          "id": "ולא",
          "sbl": "cha.Mal",
          "gloss": "he has spared",
          "lemma_strongs": "H2550"
        },
        {
          "id": "חמל",
          "sbl": "'et",
          "gloss": "[obj](m)",
          "lemma_strongs": "H0853"
        },
        {
          "id": "את",
          "sbl": "kol-",
          "gloss": "all",
          "lemma_strongs": "H3605"
        },
        {
          "id": "כל",
          "sbl": "ne.'ot",
          "gloss": "[the] settlements of",
          "lemma_strongs": "H4999"
        },
        {
          "id": "נאות",
          "sbl": "ya.'a.Ko",
          "gloss": "Jacob",
          "lemma_strongs": "H3290"
        },
        {
          "id": "יעקב",
          "sbl": "ha.Ras",
          "gloss": "he has torn down",
          "lemma_strongs": "H2040"
        },
        {
          "id": "הרס",
          "sbl": "be.'ev.ra.To",
          "gloss": "his in wrath(m)",
          "prefix_strongs": "H9003",
          "lemma_strongs": "H5678",
          "suffix_strongs": "H9023"
        },
        {
          "id": "בעברתו",
          "sbl": "miv.tze.Rei",
          "gloss": "[the] fortifications of",
          "lemma_strongs": "H4013"
        },
        {
          "id": "מבצרי",
          "sbl": "vat-",
          "gloss": "[the] daughter of",
          "lemma_strongs": "H1323"
        },
        {
          "id": "בת",
          "sbl": "ye.hu.Dah",
          "gloss": "Judah",
          "lemma_strongs": "H3063"
        },
        {
          "id": "יהודה",
          "sbl": "hi.Gi.a'",
          "gloss": "he has made [them] touch",
          "lemma_strongs": "H5060"
        },
        {
          "id": "הגיע",
          "sbl": "la.'A.retz",
          "gloss": "[to] the ground(m)",
          "prefix_strongs": "H9005",
          "lemma_strongs": "H0776"
        },
        {
          "id": "לארץ",
          "sbl": "chi.Lel",
          "gloss": "he has profaned",
          "lemma_strongs": "H2490"
        },
        {
          "id": "חלל",
          "sbl": "mam.la.Khah",
          "gloss": "[the] kingdom(m)",
          "lemma_strongs": "H4467"
        },
        {
          "id": "ממלכה",
          "sbl": "ve.sa.Rei.ha",
          "gloss": "its and princes",
          "prefix_strongs": "H9002",
          "lemma_strongs": "H8269",
          "suffix_strongs": "H9024"
        },
        {
          "id": "ושריה",
          "sbl": "Sᵉrâyâh",
          "gloss": "and Serajah",
          "lemma_strongs": null
        }
      ],
      "insights": []
    },
    {
      "verse": 3,
      "words": [
        {
          "id": "גדע",
          "sbl": "ga.Da'",
          "gloss": "has cut off(m)",
          "lemma_strongs": "H1438"
        },
        {
          "id": "בחרי",
          "sbl": "bo.cho.ri-",
          "gloss": "in [the] heat of",
          "prefix_strongs": "H9003",
          "lemma_strongs": "H2750"
        },
        {
          "id": "אף",
          "sbl": "'Af",
          "gloss": "anger",
          "lemma_strongs": "H0639"
        },
        {
          "id": "כל",
          "sbl": "kol",
          "gloss": "every",
          "lemma_strongs": "H3605"
        },
        {
          "id": "קרן",
          "sbl": "Ke.ren",
          "gloss": "[the] horn of",
          "lemma_strongs": "H7161"
        },
        {
          "id": "ישראל",
          "sbl": "Yis.ra.'El",
          "gloss": "Israel",
          "lemma_strongs": "H3478"
        },
        {
          "id": "השיב",
          "sbl": "he.Shiv",
          "gloss": "has turned back(m)",
          "lemma_strongs": "H7725"
        },
        {
          "id": "אחור",
          "sbl": "'a.Chor",
          "gloss": "backward",
          "lemma_strongs": "H0268"
        },
        {
          "id": "ימינו",
          "sbl": "ye.mi.No",
          "gloss": "his right [hand]",
          "lemma_strongs": "H3225",
          "suffix_strongs": "H9023"
        },
        {
          "id": "מפני",
          "sbl": "mi.pe.Nei",
          "gloss": "from before",
          "prefix_strongs": "H9006",
          "lemma_strongs": "H6440"
        },
        {
          "id": "אויב",
          "sbl": "'o.Yev",
          "gloss": "[the] enemy",
          "lemma_strongs": "H0341"
        },
        {
          "id": "ויבער",
          "sbl": "vai.yiv.'Ar",
          "gloss": "and has burned(m)",
          "prefix_strongs": "H9001",
          "lemma_strongs": "H1197"
        },
        {
          "id": "ביעקב",
          "sbl": "be.ya.'a.Ko",
          "gloss": "[in] Jacob",
          "prefix_strongs": "H9003",
          "lemma_strongs": "H3290"
        },
        {
          "id": "כאש",
          "sbl": "ke.'Esh",
          "gloss": "like a fire of",
          "prefix_strongs": "H9004",
          "lemma_strongs": "H0784"
        },
        {
          "id": "להבה",
          "sbl": "le.ha.Vah",
          "gloss": "flame",
          "lemma_strongs": "H3852"
        },
        {
          "id": "אכלה",
          "sbl": "'a.khe.Lah",
          "gloss": "[which] has consumed(f)",
          "lemma_strongs": "H0398"
        },
        {
          "id": "סביב",
          "sbl": "sa.Viv",
          "gloss": "all around",
          "lemma_strongs": "H5439"
        }
      ],
      "insights": []
    },
    {
      "verse": 4,
      "words": [
        {
          "id": "דרך",
          "sbl": "da.Rakh",
          "gloss": "has bent(m)",
          "lemma_strongs": "H1869"
        },
        {
          "id": "קשתו",
          "sbl": "kash.To",
          "gloss": "his bow",
          "lemma_strongs": "H7198",
          "suffix_strongs": "H9023"
        },
        {
          "id": "כאויב",
          "sbl": "ke.'o.Yev",
          "gloss": "like an enemy",
          "prefix_strongs": "H9004",
          "lemma_strongs": "H0341"
        },
        {
          "id": "נצב",
          "sbl": "ni.Tzav",
          "gloss": "[has] taken a stand",
          "lemma_strongs": "H5324"
        },
        {
          "id": "ימינו",
          "sbl": "ye.mi.No",
          "gloss": "his right [hand]",
          "lemma_strongs": "H3225",
          "suffix_strongs": "H9023"
        },
        {
          "id": "כצר",
          "sbl": "ke.Tzar",
          "gloss": "like an opponent",
          "prefix_strongs": "H9004",
          "lemma_strongs": "H6862"
        },
        {
          "id": "ויהרג",
          "sbl": "vai.ya.ha.Rog",
          "gloss": "and has killed(m)",
          "prefix_strongs": "H9001",
          "lemma_strongs": "H2026"
        },
        {
          "id": "כל",
          "sbl": "kol",
          "gloss": "all",
          "lemma_strongs": "H3605"
        },
        {
          "id": "מחמדי",
          "sbl": "ma.cha.ma.dei-",
          "gloss": "[the] delights of",
          "lemma_strongs": "H4261"
        },
        {
          "id": "עין",
          "sbl": "'A.yin",
          "gloss": "eye",
          "lemma_strongs": "H5869"
        },
        {
          "id": "באהל",
          "sbl": "be.'O.hel",
          "gloss": "in [the] tent of",
          "prefix_strongs": "H9003",
          "lemma_strongs": "H0168"
        },
        {
          "id": "בת",
          "sbl": "bat-",
          "gloss": "[the] daughter of",
          "lemma_strongs": "H1323"
        },
        {
          "id": "ציון",
          "sbl": "tzi.Yon",
          "gloss": "Zion",
          "lemma_strongs": "H6726"
        },
        {
          "id": "שפך",
          "sbl": "sha.Fakh",
          "gloss": "has poured out(m)",
          "lemma_strongs": "H8210"
        },
        {
          "id": "כאש",
          "sbl": "ka.'Esh",
          "gloss": "like [the] fire",
          "prefix_strongs": "H9004",
          "lemma_strongs": "H0784"
        },
        {
          "id": "חמתו",
          "sbl": "cha.ma.To",
          "gloss": "his rage",
          "lemma_strongs": "H2534",
          "suffix_strongs": "H9023"
        }
      ],
      "insights": []
    },
    {
      "verse": 5,
      "words": [
        {
          "id": "היה",
          "sbl": "ha.Yah",
          "gloss": "has become(m)",
          "lemma_strongs": "H1961"
        },
        {
          "id": "אדני",
          "sbl": "'a.do.Nai",
          "gloss": "[the] Lord",
          "lemma_strongs": "H0136"
        },
        {
          "id": "כאויב",
          "sbl": "ke.'o.Yev",
          "gloss": "like an enemy",
          "prefix_strongs": "H9004",
          "lemma_strongs": "H0341"
        },
        {
          "id": "בלע",
          "sbl": "bi.La'",
          "gloss": "has swallowed up(m)",
          "lemma_strongs": "H1104"
        },
        {
          "id": "ישראל",
          "sbl": "Yis.ra.'El",
          "gloss": "Israel",
          "lemma_strongs": "H3478"
        },
        {
          "id": "בלע",
          "sbl": "bi.La'",
          "gloss": "has swallowed up(m)",
          "lemma_strongs": "H1104"
        },
        {
          "id": "כל",
          "sbl": "kol-",
          "gloss": "all",
          "lemma_strongs": "H3605"
        },
        {
          "id": "ארמנותיה",
          "sbl": "'ar.me.no.Tei.ha",
          "gloss": "its palaces",
          "lemma_strongs": "H0759",
          "suffix_strongs": "H9024"
        },
        {
          "id": "שחת",
          "sbl": "shi.Chet",
          "gloss": "has ruined(m)",
          "lemma_strongs": "H7843"
        },
        {
          "id": "מבצריו",
          "sbl": "miv.tza.Rav",
          "gloss": "its fortifications",
          "lemma_strongs": "H4013",
          "suffix_strongs": "H9023"
        },
        {
          "id": "וירב",
          "sbl": "vai.Ye.rev",
          "gloss": "and has multiplied(m)",
          "prefix_strongs": "H9001",
          "lemma_strongs": "H7235"
        },
        {
          "id": "בבת",
          "sbl": "be.vat-",
          "gloss": "in [the] daughter of",
          "prefix_strongs": "H9003",
          "lemma_strongs": "H1323"
        },
        {
          "id": "יהודה",
          "sbl": "ye.hu.Dah",
          "gloss": "Judah",
          "lemma_strongs": "H3063"
        },
        {
          "id": "תאניה",
          "sbl": "ta.'a.ni.Yah",
          "gloss": "mourning",
          "lemma_strongs": "H8386"
        },
        {
          "id": "ואניה",
          "sbl": "va.'a.ni.Yah",
          "gloss": "and lamentation",
          "prefix_strongs": "H9002",
          "lemma_strongs": "H0592"
        }
      ],
      "insights": []
    },
    {
      "verse": 6,
      "words": [
        {
          "id": "ויחמס",
          "sbl": "vai.yach.Mos",
          "gloss": "and has treated violently(m)",
          "prefix_strongs": "H9001",
          "lemma_strongs": "H2554"
        },
        {
          "id": "כגן",
          "sbl": "ka.Gan",
          "gloss": "like [the] garden",
          "prefix_strongs": "H9004",
          "lemma_strongs": "H1588"
        },
        {
          "id": "שכו",
          "sbl": "su.Ko",
          "gloss": "his booth",
          "lemma_strongs": "H7900",
          "suffix_strongs": "H9023"
        },
        {
          "id": "שחת",
          "sbl": "shi.Chet",
          "gloss": "has ruined(m)",
          "lemma_strongs": "H7843"
        },
        {
          "id": "מועדו",
          "sbl": "mo.'a.Do",
          "gloss": "his appointed place",
          "lemma_strongs": "H4150",
          "suffix_strongs": "H9023"
        },
        {
          "id": "שכח",
          "sbl": "shi.Kach",
          "gloss": "has caused to be forgotten(m)",
          "lemma_strongs": "H7911"
        },
        {
          "id": "יהוה",
          "sbl": "Yah.weh",
          "gloss": "Yahweh",
          "lemma_strongs": "H3068"
        },
        {
          "id": "בציון",
          "sbl": "be.tzi.yOn",
          "gloss": "in Zion",
          "prefix_strongs": "H9003",
          "lemma_strongs": "H6726"
        },
        {
          "id": "מועד",
          "sbl": "mo.'Ed",
          "gloss": "appointed feast",
          "lemma_strongs": "H4150"
        },
        {
          "id": "ושבת",
          "sbl": "ve.sha.Bat",
          "gloss": "and sabbath",
          "prefix_strongs": "H9002",
          "lemma_strongs": "H7676"
        },
        {
          "id": "וינאץ",
          "sbl": "vai.yin.'Atz",
          "gloss": "and has spurned(m)",
          "prefix_strongs": "H9001",
          "lemma_strongs": "H5006"
        },
        {
          "id": "בזעם",
          "sbl": "be.za.'am-",
          "gloss": "in [the] indignation of",
          "prefix_strongs": "H9003",
          "lemma_strongs": "H2195"
        },
        {
          "id": "אפו",
          "sbl": "'a.Po",
          "gloss": "his anger",
          "lemma_strongs": "H0639",
          "suffix_strongs": "H9023"
        },
        {
          "id": "מלך",
          "sbl": "Me.lekh",
          "gloss": "king",
          "lemma_strongs": "H4428"
        },
        {
          "id": "וכהן",
          "sbl": "ve.kho.Hen",
          "gloss": "and priest",
          "prefix_strongs": "H9002",
          "lemma_strongs": "H3548"
        }
      ],
      "insights": []
    },
    {
      "verse": 7,
      "words": [
        {
          "id": "זנח",
          "sbl": "za.Nach",
          "gloss": "has rejected(m)",
          "lemma_strongs": "H2186"
        },
        {
          "id": "אדני",
          "sbl": "'a.do.Nai",
          "gloss": "[the] Lord",
          "lemma_strongs": "H0136"
        },
        {
          "id": "מזבחו",
          "sbl": "miz.be.Cho",
          "gloss": "his altar",
          "lemma_strongs": "H4196",
          "suffix_strongs": "H9023"
        },
        {
          "id": "נאר",
          "sbl": "ni.'Er",
          "gloss": "has repudiated(m)",
          "lemma_strongs": "H5010"
        },
        {
          "id": "מקדשו",
          "sbl": "mik.da.Sho",
          "gloss": "his sanctuary",
          "lemma_strongs": "H4720",
          "suffix_strongs": "H9023"
        },
        {
          "id": "הסגיר",
          "sbl": "his.Gir",
          "gloss": "has delivered up(m)",
          "lemma_strongs": "H5462"
        },
        {
          "id": "ביד",
          "sbl": "be.yad-",
          "gloss": "in [the] hand of",
          "prefix_strongs": "H9003",
          "lemma_strongs": "H3027"
        },
        {
          "id": "אויב",
          "sbl": "'o.Yev",
          "gloss": "an enemy",
          "lemma_strongs": "H0341"
        },
        {
          "id": "חומת",
          "sbl": "cho.Mot",
          "gloss": "[the] walls of",
          "lemma_strongs": "H2346"
        },
        {
          "id": "ארמנותיה",
          "sbl": "'ar.me.no.Tei.ha",
          "gloss": "its palaces",
          "lemma_strongs": "H0759",
          "suffix_strongs": "H9024"
        },
        {
          "id": "קול",
          "sbl": "Kol",
          "gloss": "voice",
          "lemma_strongs": "H6963"
        },
        {
          "id": "נתנו",
          "sbl": "na.te.Nu",
          "gloss": "people have given forth",
          "lemma_strongs": "H5414"
        },
        {
          "id": "בבית",
          "sbl": "be.veit-",
          "gloss": "in [the] house of",
          "prefix_strongs": "H9003",
          "lemma_strongs": "H1004"
        },
        {
          "id": "יהוה",
          "sbl": "Yah.weh",
          "gloss": "Yahweh",
          "lemma_strongs": "H3068"
        },
        {
          "id": "כיום",
          "sbl": "ke.Yom",
          "gloss": "like [the] day of",
          "prefix_strongs": "H9004",
          "lemma_strongs": "H3117"
        },
        {
          "id": "מועד",
          "sbl": "mo.'Ed",
          "gloss": "an appointed feast",
          "lemma_strongs": "H4150"
        }
      ],
      "insights": []
    },
    {
      "verse": 8,
      "words": [
        {
          "id": "חשב",
          "sbl": "cha.Shav",
          "gloss": "has planned(m)",
          "lemma_strongs": "H2803"
        },
        {
          "id": "יהוה",
          "sbl": "Yah.weh",
          "gloss": "Yahweh",
          "lemma_strongs": "H3068"
        },
        {
          "id": "להשחית",
          "sbl": "le.hash.Chit",
          "gloss": "to destroy",
          "prefix_strongs": "H9005",
          "lemma_strongs": "H7843"
        },
        {
          "id": "חומת",
          "sbl": "cho.Mat",
          "gloss": "[the] wall of",
          "lemma_strongs": "H2346"
        },
        {
          "id": "בת",
          "sbl": "bat-",
          "gloss": "[the] daughter of",
          "lemma_strongs": "H1323"
        },
        {
          "id": "ציון",
          "sbl": "tzi.Yon",
          "gloss": "Zion",
          "lemma_strongs": "H6726"
        },
        {
          "id": "נטה",
          "sbl": "Na.tah",
          "gloss": "has stretched out(m)",
          "lemma_strongs": "H5186"
        },
        {
          "id": "קו",
          "sbl": "Kav",
          "gloss": "a measuring-line",
          "lemma_strongs": "H6957"
        },
        {
          "id": "לא",
          "sbl": "lo'-",
          "gloss": "not",
          "lemma_strongs": "H3808"
        },
        {
          "id": "השיב",
          "sbl": "he.Shiv",
          "gloss": "has turned back(m)",
          "lemma_strongs": "H7725"
        },
        {
          "id": "ידו",
          "sbl": "ya.Do",
          "gloss": "his hand",
          "lemma_strongs": "H3027",
          "suffix_strongs": "H9023"
        },
        {
          "id": "מבלע",
          "sbl": "mi.ba.Le.a'",
          "gloss": "from swallowing up",
          "prefix_strongs": "H9006",
          "lemma_strongs": "H1104"
        },
        {
          "id": "ויאבל",
          "sbl": "vai.ya.'a.vel-",
          "gloss": "and has caused to mourn(m)",
          "prefix_strongs": "H9001",
          "lemma_strongs": "H0056"
        },
        {
          "id": "חל",
          "sbl": "chel",
          "gloss": "rampart",
          "lemma_strongs": "H2426"
        },
        {
          "id": "וחומה",
          "sbl": "ve.cho.Mah",
          "gloss": "and wall",
          "prefix_strongs": "H9002",
          "lemma_strongs": "H2346"
        },
        {
          "id": "יחדו",
          "sbl": "yach.Dav",
          "gloss": "together",
          "lemma_strongs": "H3162"
        },
        {
          "id": "אמללו",
          "sbl": "'um.La.lu",
          "gloss": "have languished",
          "lemma_strongs": "H0535"
        }
      ],
      "insights": []
    },
    {
      "verse": 9,
      "words": [
        {
          "id": "טבעו",
          "sbl": "ta.ve.'U",
          "gloss": "have sunk",
          "lemma_strongs": "H2883"
        },
        {
          "id": "בארץ",
          "sbl": "va.'A.retz",
          "gloss": "in the ground",
          "prefix_strongs": "H9003",
          "lemma_strongs": "H0776"
        },
        {
          "id": "שעריה",
          "sbl": "she.'a.Rei.ha",
          "gloss": "its gates",
          "lemma_strongs": "H8179",
          "suffix_strongs": "H9024"
        },
        {
          "id": "אבד",
          "sbl": "'i.Bad",
          "gloss": "has destroyed(m)",
          "lemma_strongs": "H0006"
        },
        {
          "id": "ושבר",
          "sbl": "ve.shi.Bar",
          "gloss": "and has broken(m)",
          "prefix_strongs": "H9002",
          "lemma_strongs": "H7665"
        },
        {
          "id": "בריחיה",
          "sbl": "be.ri.Chei.ha",
          "gloss": "its bars",
          "lemma_strongs": "H1280",
          "suffix_strongs": "H9024"
        },
        {
          "id": "מלכה",
          "sbl": "mal.Kah",
          "gloss": "its king",
          "lemma_strongs": "H4428",
          "suffix_strongs": "H9024"
        },
        {
          "id": "ושריה",
          "sbl": "ve.sa.Rei.ha",
          "gloss": "its and princes",
          "prefix_strongs": "H9002",
          "lemma_strongs": "H8269",
          "suffix_strongs": "H9024"
        },
        {
          "id": "בגוים",
          "sbl": "va.go.Yim",
          "gloss": "[are] among the nations",
          "prefix_strongs": "H9003",
          "lemma_strongs": "H1471"
        },
        {
          "id": "אין",
          "sbl": "'ein",
          "gloss": "there not",
          "lemma_strongs": "H0369"
        },
        {
          "id": "תורה",
          "sbl": "to.Rah",
          "gloss": "[is] instruction",
          "lemma_strongs": "H8451"
        },
        {
          "id": "גם",
          "sbl": "gam-",
          "gloss": "also",
          "lemma_strongs": "H1571"
        },
        {
          "id": "נביאיה",
          "sbl": "ne.vi.'Ei.ha",
          "gloss": "its prophets",
          "lemma_strongs": "H5030",
          "suffix_strongs": "H9024"
        },
        {
          "id": "לא",
          "sbl": "lo'-",
          "gloss": "not",
          "lemma_strongs": "H3808"
        },
        {
          "id": "מצאו",
          "sbl": "ma.tze.'U",
          "gloss": "have found",
          "lemma_strongs": "H4672"
        },
        {
          "id": "חזון",
          "sbl": "cha.Zon",
          "gloss": "a vision",
          "lemma_strongs": "H2377"
        },
        {
          "id": "מיהוה",
          "sbl": "me.Yah.weh",
          "gloss": "from Yahweh",
          "prefix_strongs": "H9006",
          "lemma_strongs": "H3068"
        }
      ],
      "insights": []
    },
    {
      "verse": 10,
      "words": [
        {
          "id": "ישבו",
          "sbl": "ye.she.Vu",
          "gloss": "sit(m)",
          "lemma_strongs": "H3427"
        },
        {
          "id": "לארץ",
          "sbl": "la.'A.retz",
          "gloss": "to the ground",
          "prefix_strongs": "H9005",
          "lemma_strongs": "H0776"
        },
        {
          "id": "ידמו",
          "sbl": "yi.de.Mu",
          "gloss": "are silent(m)",
          "lemma_strongs": "H1826"
        },
        {
          "id": "זקני",
          "sbl": "zik.Nei",
          "gloss": "[the] elders of",
          "lemma_strongs": "H2205"
        },
        {
          "id": "בת",
          "sbl": "vat-",
          "gloss": "[the] daughter of",
          "lemma_strongs": "H1323"
        },
        {
          "id": "ציון",
          "sbl": "tzi.Yon",
          "gloss": "Zion",
          "lemma_strongs": "H6726"
        },
        {
          "id": "העלו",
          "sbl": "he.'e.Lu",
          "gloss": "have caused to rise",
          "lemma_strongs": "H5927"
        },
        {
          "id": "עפר",
          "sbl": "'a.Far",
          "gloss": "dust",
          "lemma_strongs": "H6083"
        },
        {
          "id": "על",
          "sbl": "'al-",
          "gloss": "on",
          "lemma_strongs": "H5921"
        },
        {
          "id": "ראשם",
          "sbl": "ro.Sham",
          "gloss": "their head",
          "lemma_strongs": "H7218",
          "suffix_strongs": "H9028"
        },
        {
          "id": "חגרו",
          "sbl": "cha.ge.Ru",
          "gloss": "have girded on",
          "lemma_strongs": "H2296"
        },
        {
          "id": "שקים",
          "sbl": "sa.Kim",
          "gloss": "sackcloth[s]",
          "lemma_strongs": "H8242"
        },
        {
          "id": "הורידו",
          "sbl": "ho.Ri.du",
          "gloss": "have brought down",
          "lemma_strongs": "H3381"
        },
        {
          "id": "לארץ",
          "sbl": "la.'A.retz",
          "gloss": "to the ground",
          "prefix_strongs": "H9005",
          "lemma_strongs": "H0776"
        },
        {
          "id": "ראשן",
          "sbl": "ro.Shan",
          "gloss": "their head",
          "lemma_strongs": "H7218",
          "suffix_strongs": "H9029"
        },
        {
          "id": "בתולת",
          "sbl": "be.tu.Lot",
          "gloss": "[the] virgins of",
          "lemma_strongs": "H1330"
        },
        {
          "id": "ירושלם",
          "sbl": "ye.ru.sha.Lim",
          "gloss": "Jerusalem",
          "lemma_strongs": "H3389"
        }
      ],
      "insights": []
    },
    {
      "verse": 11,
      "words": [
        {
          "id": "כלו",
          "sbl": "ka.Lu",
          "gloss": "have failed",
          "lemma_strongs": "H3615"
        },
        {
          "id": "בדמעות",
          "sbl": "va.de.ma.'ot",
          "gloss": "by [the] tears",
          "prefix_strongs": "H9003",
          "lemma_strongs": "H1832"
        },
        {
          "id": "עיני",
          "sbl": "'ei.Nai",
          "gloss": "eyes my",
          "lemma_strongs": "H5869",
          "suffix_strongs": "H9020"
        },
        {
          "id": "חמרמרו",
          "sbl": "cho.mar.me.Ru",
          "gloss": "are in turmoil",
          "lemma_strongs": "H2560"
        },
        {
          "id": "מעי",
          "sbl": "me.'Ai",
          "gloss": "inward parts my",
          "lemma_strongs": "H4578",
          "suffix_strongs": "H9020"
        },
        {
          "id": "נשפך",
          "sbl": "nish.Pakh",
          "gloss": "has been poured out(m)",
          "lemma_strongs": "H8210"
        },
        {
          "id": "לארץ",
          "sbl": "la.'A.retz",
          "gloss": "to the ground",
          "prefix_strongs": "H9005",
          "lemma_strongs": "H0776"
        },
        {
          "id": "כבדי",
          "sbl": "ke.ve.Di",
          "gloss": "liver my",
          "lemma_strongs": "H3516",
          "suffix_strongs": "H9020"
        },
        {
          "id": "על",
          "sbl": "'al-",
          "gloss": "on",
          "lemma_strongs": "H5921"
        },
        {
          "id": "שבר",
          "sbl": "She.ver",
          "gloss": "[the] brokenness of",
          "lemma_strongs": "H7667"
        },
        {
          "id": "בת",
          "sbl": "bat-",
          "gloss": "[the] daughter of",
          "lemma_strongs": "H1323"
        },
        {
          "id": "עמי",
          "sbl": "'a.Mi",
          "gloss": "people my",
          "lemma_strongs": "H5971",
          "suffix_strongs": "H9020"
        },
        {
          "id": "בעטף",
          "sbl": "be.'a.Tef",
          "gloss": "because faint",
          "prefix_strongs": "H9003",
          "lemma_strongs": "H5848"
        },
        {
          "id": "עולל",
          "sbl": "o.Lel",
          "gloss": "child",
          "lemma_strongs": "H5768"
        },
        {
          "id": "ויונק",
          "sbl": "ve.yo.Nek",
          "gloss": "and suckling-child",
          "prefix_strongs": "H9002",
          "lemma_strongs": "H3243"
        },
        {
          "id": "ברחבות",
          "sbl": "bir.cho.Vot",
          "gloss": "in [the] open places of",
          "prefix_strongs": "H9003",
          "lemma_strongs": "H7339"
        },
        {
          "id": "קריה",
          "sbl": "kir.Yah",
          "gloss": "a town",
          "lemma_strongs": "H7151"
        }
      ],
      "insights": []
    },
    {
      "verse": 12,
      "words": [
        {
          "id": "לאמתם",
          "sbl": "le.'i.mo.Tam",
          "gloss": "their to mothers",
          "prefix_strongs": "H9005",
          "lemma_strongs": "H0517",
          "suffix_strongs": "H9028"
        },
        {
          "id": "יאמרו",
          "sbl": "yo.me.Ru",
          "gloss": "say(m)",
          "lemma_strongs": "H0559"
        },
        {
          "id": "איה",
          "sbl": "'ai.Yeh",
          "gloss": "where?",
          "lemma_strongs": "H0346"
        },
        {
          "id": "דגן",
          "sbl": "da.Gan",
          "gloss": "[are] grain",
          "lemma_strongs": "H1715"
        },
        {
          "id": "ויין",
          "sbl": "va.Ya.yin",
          "gloss": "and wine",
          "prefix_strongs": "H9002",
          "lemma_strongs": "H3196"
        },
        {
          "id": "בהתעטפם",
          "sbl": "be.hit.'a.te.Fam",
          "gloss": "when faint away they",
          "prefix_strongs": "H9003",
          "lemma_strongs": "H5848",
          "suffix_strongs": "H9048"
        },
        {
          "id": "כחלל",
          "sbl": "ke.cha.Lal",
          "gloss": "like [the] [one] fatally wounded",
          "prefix_strongs": "H9004",
          "lemma_strongs": "H2491"
        },
        {
          "id": "ברחבות",
          "sbl": "bir.cho.Vot",
          "gloss": "in [the] open places of",
          "prefix_strongs": "H9003",
          "lemma_strongs": "H7339"
        },
        {
          "id": "עיר",
          "sbl": "'Ir",
          "gloss": "a city",
          "lemma_strongs": "H5892"
        },
        {
          "id": "בהשתפך",
          "sbl": "be.hish.ta.Pekh",
          "gloss": "when pours itself out",
          "prefix_strongs": "H9003",
          "lemma_strongs": "H8210"
        },
        {
          "id": "נפשם",
          "sbl": "naf.Sham",
          "gloss": "their life",
          "lemma_strongs": "H5315",
          "suffix_strongs": "H9028"
        },
        {
          "id": "אל",
          "sbl": "'el-",
          "gloss": "to",
          "lemma_strongs": "H0413"
        },
        {
          "id": "חיק",
          "sbl": "cheik",
          "gloss": "[the] bosom of",
          "lemma_strongs": "H2436"
        },
        {
          "id": "אמתם",
          "sbl": "'i.mo.Tam",
          "gloss": "their mothers",
          "lemma_strongs": "H0517",
          "suffix_strongs": "H9028"
        }
      ],
      "insights": []
    },
    {
      "verse": 13,
      "words": [
        {
          "id": "מה",
          "sbl": "mah-",
          "gloss": "what?",
          "lemma_strongs": "H4100"
        },
        {
          "id": "אעידך",
          "sbl": "'a.'i.Dekh",
          "gloss": "will I testify for you",
          "lemma_strongs": "H5749",
          "suffix_strongs": "H9032"
        },
        {
          "id": "מה",
          "sbl": "mah",
          "gloss": "what?",
          "lemma_strongs": "H4100"
        },
        {
          "id": "אדמה",
          "sbl": "'a.da.meh-",
          "gloss": "will I liken",
          "lemma_strongs": "H1819"
        },
        {
          "id": "לך",
          "sbl": "Lakh",
          "gloss": "to you",
          "prefix_strongs": "H9005",
          "lemma_strongs": "H9032"
        },
        {
          "id": "הבת",
          "sbl": "ha.Bat",
          "gloss": "O daughter of",
          "prefix_strongs": "H9009",
          "lemma_strongs": "H1323"
        },
        {
          "id": "ירושלם",
          "sbl": "ye.Ru.sha.Lim",
          "gloss": "Jerusalem",
          "lemma_strongs": "H3389"
        },
        {
          "id": "מה",
          "sbl": "mah",
          "gloss": "what?",
          "lemma_strongs": "H4100"
        },
        {
          "id": "אשוה",
          "sbl": "'ash.veh-",
          "gloss": "will I make equal",
          "lemma_strongs": "H7737"
        },
        {
          "id": "לך",
          "sbl": "loKh",
          "gloss": "to you",
          "prefix_strongs": "H9005",
          "lemma_strongs": "H9032"
        },
        {
          "id": "ואנחמך",
          "sbl": "va.'a.na.cha.Mekh",
          "gloss": "so I may comfort you",
          "prefix_strongs": "H9002",
          "lemma_strongs": "H5162",
          "suffix_strongs": "H9032"
        },
        {
          "id": "בתולת",
          "sbl": "be.tu.Lat",
          "gloss": "O virgin of",
          "lemma_strongs": "H1330"
        },
        {
          "id": "בת",
          "sbl": "bat-",
          "gloss": "[the] daughter of",
          "lemma_strongs": "H1323"
        },
        {
          "id": "ציון",
          "sbl": "tzi.Yon",
          "gloss": "Zion",
          "lemma_strongs": "H6726"
        },
        {
          "id": "כי",
          "sbl": "ki-",
          "gloss": "for",
          "lemma_strongs": "H3588"
        },
        {
          "id": "גדול",
          "sbl": "ga.Dol",
          "gloss": "[is] great",
          "lemma_strongs": "H1419"
        },
        {
          "id": "כים",
          "sbl": "kai.Yam",
          "gloss": "like the sea",
          "prefix_strongs": "H9004",
          "lemma_strongs": "H3220"
        },
        {
          "id": "שברך",
          "sbl": "shiv.Rekh",
          "gloss": "your brokenness",
          "lemma_strongs": "H7667",
          "suffix_strongs": "H9022"
        },
        {
          "id": "מי",
          "sbl": "mi",
          "gloss": "who?",
          "lemma_strongs": "H4310"
        },
        {
          "id": "ירפא",
          "sbl": "yir.pa'-",
          "gloss": "will heal(m)",
          "lemma_strongs": "H7495"
        },
        {
          "id": "לך",
          "sbl": "Lakh",
          "gloss": "[to] you",
          "prefix_strongs": "H9005",
          "lemma_strongs": "H9032"
        }
      ],
      "insights": []
    },
    {
      "verse": 14,
      "words": [
        {
          "id": "נביאיך",
          "sbl": "ne.vi.'A.yikh",
          "gloss": "your prophets",
          "lemma_strongs": "H5030",
          "suffix_strongs": "H9022"
        },
        {
          "id": "חזו",
          "sbl": "Cha.zu",
          "gloss": "have seen",
          "lemma_strongs": "H2372"
        },
        {
          "id": "לך",
          "sbl": "loKh",
          "gloss": "for you",
          "prefix_strongs": "H9005",
          "lemma_strongs": "H9032"
        },
        {
          "id": "שוא",
          "sbl": "shav'",
          "gloss": "worthlessness",
          "lemma_strongs": "H7723"
        },
        {
          "id": "ותפל",
          "sbl": "ve.ta.Fel",
          "gloss": "and sham",
          "prefix_strongs": "H9002",
          "lemma_strongs": "H8602"
        },
        {
          "id": "ולא",
          "sbl": "ve.lo'-",
          "gloss": "and not",
          "prefix_strongs": "H9002",
          "lemma_strongs": "H3808"
        },
        {
          "id": "גלו",
          "sbl": "gi.Lu",
          "gloss": "have made known",
          "lemma_strongs": "H1540"
        },
        {
          "id": "על",
          "sbl": "'al-",
          "gloss": "on",
          "lemma_strongs": "H5921"
        },
        {
          "id": "עונך",
          "sbl": "'a.vo.Nekh",
          "gloss": "your iniquity",
          "lemma_strongs": "H5771",
          "suffix_strongs": "H9022"
        },
        {
          "id": "להשיב",
          "sbl": "le.ha.Shiv",
          "gloss": "to turn back",
          "prefix_strongs": "H9005",
          "lemma_strongs": "H7725"
        },
        {
          "id": "שביתך",
          "sbl": "she.vi.tekh",
          "gloss": "your captivity",
          "lemma_strongs": "H7622",
          "suffix_strongs": "H9022"
        },
        {
          "id": "שבותך",
          "sbl": "vai.Ye.che.zu",
          "gloss": "and they have seen",
          "prefix_strongs": "H9001",
          "lemma_strongs": "H2372"
        },
        {
          "id": "ויחזו",
          "sbl": "Lakh",
          "gloss": "for you(m)",
          "prefix_strongs": "H9005",
          "lemma_strongs": "H9032"
        },
        {
          "id": "לך",
          "sbl": "mas.'ot",
          "gloss": "oracles of",
          "lemma_strongs": "H4853"
        },
        {
          "id": "משאות",
          "sbl": "shav'",
          "gloss": "worthlessness",
          "lemma_strongs": "H7723"
        },
        {
          "id": "שוא",
          "sbl": "u.ma.du.Chim",
          "gloss": "and enticement[s]",
          "prefix_strongs": "H9002",
          "lemma_strongs": "H4065"
        },
        {
          "id": "ומדוחים",
          "sbl": "maddûwach",
          "gloss": "and seduction",
          "lemma_strongs": null
        }
      ],
      "insights": []
    },
    {
      "verse": 15,
      "words": [
        {
          "id": "ספקו",
          "sbl": "sa.fe.Ku",
          "gloss": "have clapped",
          "lemma_strongs": "H5606"
        },
        {
          "id": "עליך",
          "sbl": "'a.La.yikh",
          "gloss": "on you",
          "lemma_strongs": "H5921",
          "suffix_strongs": "H9032"
        },
        {
          "id": "כפים",
          "sbl": "ka.Pa.yim",
          "gloss": "hands",
          "lemma_strongs": "H3709"
        },
        {
          "id": "כל",
          "sbl": "kol-",
          "gloss": "all",
          "lemma_strongs": "H3605"
        },
        {
          "id": "עברי",
          "sbl": "oe.rei",
          "gloss": "[those who] pass by of",
          "lemma_strongs": "H5674"
        },
        {
          "id": "דרך",
          "sbl": "De.rekh",
          "gloss": "[the] road",
          "lemma_strongs": "H1870"
        },
        {
          "id": "שרקו",
          "sbl": "sha.re.Ku",
          "gloss": "have hissed",
          "lemma_strongs": "H8319"
        },
        {
          "id": "וינעו",
          "sbl": "vai.ya.Ni.'u",
          "gloss": "and have shaken(m)",
          "prefix_strongs": "H9001",
          "lemma_strongs": "H5128"
        },
        {
          "id": "ראשם",
          "sbl": "ro.Sham",
          "gloss": "their head",
          "lemma_strongs": "H7218",
          "suffix_strongs": "H9028"
        },
        {
          "id": "על",
          "sbl": "'al-",
          "gloss": "on",
          "lemma_strongs": "H5921"
        },
        {
          "id": "בת",
          "sbl": "bat",
          "gloss": "[the] daughter of",
          "lemma_strongs": "H1323"
        },
        {
          "id": "ירושלם",
          "sbl": "ye.ru.sha.Lim",
          "gloss": "Jerusalem",
          "lemma_strongs": "H3389"
        },
        {
          "id": "הזאת",
          "sbl": "ha.Zot",
          "gloss": "¿ [is] this",
          "prefix_strongs": "H9008",
          "lemma_strongs": "H2063"
        },
        {
          "id": "העיר",
          "sbl": "ha.'Ir",
          "gloss": "the city",
          "prefix_strongs": "H9009",
          "lemma_strongs": "H5892"
        },
        {
          "id": "שיאמרו",
          "sbl": "shei.yo.me.Ru",
          "gloss": "that people said",
          "prefix_strongs": "H9007",
          "lemma_strongs": "H0559"
        },
        {
          "id": "כלילת",
          "sbl": "ke.Li.lat",
          "gloss": "perfect of",
          "lemma_strongs": "H3632"
        },
        {
          "id": "יפי",
          "sbl": "Yo.fi",
          "gloss": "beauty",
          "lemma_strongs": "H3308"
        },
        {
          "id": "משוש",
          "sbl": "ma.Sos",
          "gloss": "a joy",
          "lemma_strongs": "H4885"
        },
        {
          "id": "לכל",
          "sbl": "le.khol",
          "gloss": "to all",
          "prefix_strongs": "H9005",
          "lemma_strongs": "H3605"
        },
        {
          "id": "הארץ",
          "sbl": "ha.'A.retz",
          "gloss": "the earth",
          "prefix_strongs": "H9009",
          "lemma_strongs": "H0776"
        }
      ],
      "insights": []
    },
    {
      "verse": 16,
      "words": [
        {
          "id": "פצו",
          "sbl": "pa.Tzu",
          "gloss": "have opened",
          "lemma_strongs": "H6475"
        },
        {
          "id": "עליך",
          "sbl": "'a.La.yikh",
          "gloss": "on you",
          "lemma_strongs": "H5921",
          "suffix_strongs": "H9032"
        },
        {
          "id": "פיהם",
          "sbl": "pi.Hem",
          "gloss": "their mouth",
          "lemma_strongs": "H6310",
          "suffix_strongs": "H9028"
        },
        {
          "id": "כל",
          "sbl": "kol-",
          "gloss": "all",
          "lemma_strongs": "H3605"
        },
        {
          "id": "אויביך",
          "sbl": "'oy.Va.yikh",
          "gloss": "your enemies",
          "lemma_strongs": "H0341",
          "suffix_strongs": "H9022"
        },
        {
          "id": "שרקו",
          "sbl": "sha.re.Ku",
          "gloss": "have hissed",
          "lemma_strongs": "H8319"
        },
        {
          "id": "ויחרקו",
          "sbl": "vai.ya.char.ku-",
          "gloss": "and have gnashed(m)",
          "prefix_strongs": "H9001",
          "lemma_strongs": "H2786"
        },
        {
          "id": "שן",
          "sbl": "Shen",
          "gloss": "a tooth",
          "lemma_strongs": "H8127"
        },
        {
          "id": "אמרו",
          "sbl": "'a.me.Ru",
          "gloss": "said",
          "lemma_strongs": "H0559"
        },
        {
          "id": "בלענו",
          "sbl": "bi.La.'e.nu",
          "gloss": "we have swallowed up",
          "lemma_strongs": "H1104"
        },
        {
          "id": "אך",
          "sbl": "'akh",
          "gloss": "surely",
          "lemma_strongs": "H0389"
        },
        {
          "id": "זה",
          "sbl": "zeh",
          "gloss": "this",
          "lemma_strongs": "H2088"
        },
        {
          "id": "היום",
          "sbl": "hai.Yom",
          "gloss": "[is] the day",
          "prefix_strongs": "H9009",
          "lemma_strongs": "H3117"
        },
        {
          "id": "שקוינהו",
          "sbl": "she.ki.vi.Nu.hu",
          "gloss": "that we have waited for it",
          "prefix_strongs": "H9007",
          "lemma_strongs": "H6960",
          "suffix_strongs": "H9033"
        },
        {
          "id": "מצאנו",
          "sbl": "ma.Tza.nu",
          "gloss": "we have found",
          "lemma_strongs": "H4672"
        },
        {
          "id": "ראינו",
          "sbl": "ra.'I.nu",
          "gloss": "we have seen",
          "lemma_strongs": "H7200"
        }
      ],
      "insights": []
    },
    {
      "verse": 17,
      "words": [
        {
          "id": "עשה",
          "sbl": "'a.Sah",
          "gloss": "has done(m)",
          "lemma_strongs": "H6213"
        },
        {
          "id": "יהוה",
          "sbl": "Yah.weh",
          "gloss": "Yahweh",
          "lemma_strongs": "H3068"
        },
        {
          "id": "אשר",
          "sbl": "'a.Sher",
          "gloss": "what",
          "lemma_strongs": "H0834"
        },
        {
          "id": "זמם",
          "sbl": "za.Mam",
          "gloss": "purposed(m)",
          "lemma_strongs": "H2161"
        },
        {
          "id": "בצע",
          "sbl": "bi.Tza'",
          "gloss": "has fulfilled(m)",
          "lemma_strongs": "H1214"
        },
        {
          "id": "אמרתו",
          "sbl": "'em.ra.To",
          "gloss": "his word",
          "lemma_strongs": "H0565",
          "suffix_strongs": "H9023"
        },
        {
          "id": "אשר",
          "sbl": "'a.Sher",
          "gloss": "which",
          "lemma_strongs": "H0834"
        },
        {
          "id": "צוה",
          "sbl": "tzi.Vah",
          "gloss": "commanded(m)",
          "lemma_strongs": "H6680"
        },
        {
          "id": "מימי",
          "sbl": "mi.mei-",
          "gloss": "from days of",
          "prefix_strongs": "H9006",
          "lemma_strongs": "H3117"
        },
        {
          "id": "קדם",
          "sbl": "Ke.dem",
          "gloss": "antiquity",
          "lemma_strongs": "H6924"
        },
        {
          "id": "הרס",
          "sbl": "ha.Ras",
          "gloss": "has torn down(m)",
          "lemma_strongs": "H2040"
        },
        {
          "id": "ולא",
          "sbl": "ve.Lo'",
          "gloss": "and not",
          "prefix_strongs": "H9002",
          "lemma_strongs": "H3808"
        },
        {
          "id": "חמל",
          "sbl": "cha.Mal",
          "gloss": "has spared(m)",
          "lemma_strongs": "H2550"
        },
        {
          "id": "וישמח",
          "sbl": "vay.sa.Mach",
          "gloss": "and has caused to rejoice(m)",
          "prefix_strongs": "H9001",
          "lemma_strongs": "H8055"
        },
        {
          "id": "עליך",
          "sbl": "'a.La.yikh",
          "gloss": "on you",
          "lemma_strongs": "H5921",
          "suffix_strongs": "H9032"
        },
        {
          "id": "אויב",
          "sbl": "'o.Yev",
          "gloss": "an enemy",
          "lemma_strongs": "H0341"
        },
        {
          "id": "הרים",
          "sbl": "he.Rim",
          "gloss": "has lifted up(m)",
          "lemma_strongs": "H7311"
        },
        {
          "id": "קרן",
          "sbl": "Ke.ren",
          "gloss": "[the] horn of",
          "lemma_strongs": "H7161"
        },
        {
          "id": "צריך",
          "sbl": "tza.Ra.yikh",
          "gloss": "your opponents",
          "lemma_strongs": "H6862",
          "suffix_strongs": "H9022"
        }
      ],
      "insights": []
    },
    {
      "verse": 18,
      "words": [
        {
          "id": "צעק",
          "sbl": "tza.'Ak",
          "gloss": "has cried out(m)",
          "lemma_strongs": "H6817"
        },
        {
          "id": "לבם",
          "sbl": "li.Bam",
          "gloss": "their heart",
          "lemma_strongs": "H3820",
          "suffix_strongs": "H9028"
        },
        {
          "id": "אל",
          "sbl": "'el-",
          "gloss": "to",
          "lemma_strongs": "H0413"
        },
        {
          "id": "אדני",
          "sbl": "'a.do.Nai",
          "gloss": "[the] Lord",
          "lemma_strongs": "H0136"
        },
        {
          "id": "חומת",
          "sbl": "cho.Mat",
          "gloss": "O wall of",
          "lemma_strongs": "H2346"
        },
        {
          "id": "בת",
          "sbl": "bat-",
          "gloss": "[the] daughter of",
          "lemma_strongs": "H1323"
        },
        {
          "id": "ציון",
          "sbl": "Tzi.yon",
          "gloss": "Zion",
          "lemma_strongs": "H6726"
        },
        {
          "id": "הורידי",
          "sbl": "ho.Ri.di",
          "gloss": "send down",
          "lemma_strongs": "H3381"
        },
        {
          "id": "כנחל",
          "sbl": "kha.Na.chal",
          "gloss": "like [the] river",
          "prefix_strongs": "H9004",
          "lemma_strongs": "H5158"
        },
        {
          "id": "דמעה",
          "sbl": "dim.'Ah",
          "gloss": "tear[s]",
          "lemma_strongs": "H1832"
        },
        {
          "id": "יומם",
          "sbl": "yo.Mam",
          "gloss": "by day",
          "lemma_strongs": "H3119"
        },
        {
          "id": "ולילה",
          "sbl": "va.Lay.lah",
          "gloss": "and night",
          "prefix_strongs": "H9002",
          "lemma_strongs": "H3915"
        },
        {
          "id": "אל",
          "sbl": "'al-",
          "gloss": "may not",
          "lemma_strongs": "H0408"
        },
        {
          "id": "תתני",
          "sbl": "ti.te.Ni",
          "gloss": "you give",
          "lemma_strongs": "H5414"
        },
        {
          "id": "פוגת",
          "sbl": "fu.Gat",
          "gloss": "rest",
          "lemma_strongs": "H6314"
        },
        {
          "id": "לך",
          "sbl": "Lakh",
          "gloss": "to yourself",
          "prefix_strongs": "H9005",
          "lemma_strongs": "H9032"
        },
        {
          "id": "אל",
          "sbl": "'al-",
          "gloss": "may not",
          "lemma_strongs": "H0408"
        },
        {
          "id": "תדם",
          "sbl": "ti.Dom",
          "gloss": "be still(f)",
          "lemma_strongs": "H1826"
        },
        {
          "id": "בת",
          "sbl": "bat-",
          "gloss": "[the] daughter of",
          "lemma_strongs": "H1323"
        },
        {
          "id": "עינך",
          "sbl": "'ei.Nekh",
          "gloss": "your eye",
          "lemma_strongs": "H5869",
          "suffix_strongs": "H9022"
        }
      ],
      "insights": []
    },
    {
      "verse": 19,
      "words": [
        {
          "id": "קומי",
          "sbl": "Ku.mi",
          "gloss": "arise",
          "lemma_strongs": "H6965"
        },
        {
          "id": "רני",
          "sbl": "Ro.ni",
          "gloss": "cry out",
          "lemma_strongs": "H7442"
        },
        {
          "id": "בליל",
          "sbl": "va.la.yil",
          "gloss": "in the night",
          "prefix_strongs": "H9003",
          "lemma_strongs": "H3915"
        },
        {
          "id": "בלילה",
          "sbl": "le.roSh",
          "gloss": "to [the] head of",
          "prefix_strongs": "H9005",
          "lemma_strongs": "H7218"
        },
        {
          "id": "לראש",
          "sbl": "'ash.mu.Rot",
          "gloss": "[the] night-watches",
          "lemma_strongs": "H0821"
        },
        {
          "id": "אשמרות",
          "sbl": "shif.Khi",
          "gloss": "pour out",
          "lemma_strongs": "H8210"
        },
        {
          "id": "שפכי",
          "sbl": "kha.Ma.yim",
          "gloss": "like [the] water",
          "prefix_strongs": "H9004",
          "lemma_strongs": "H4325"
        },
        {
          "id": "כמים",
          "sbl": "li.Bekh",
          "gloss": "your heart",
          "lemma_strongs": "H3820",
          "suffix_strongs": "H9022"
        },
        {
          "id": "לבך",
          "sbl": "No.khach",
          "gloss": "before",
          "lemma_strongs": "H5227"
        },
        {
          "id": "נכח",
          "sbl": "pe.Nei",
          "gloss": "[the] presence of",
          "lemma_strongs": "H6440"
        },
        {
          "id": "פני",
          "sbl": "'a.do.Nai",
          "gloss": "[the] Lord",
          "lemma_strongs": "H0136"
        },
        {
          "id": "אדני",
          "sbl": "se.'I",
          "gloss": "lift up",
          "lemma_strongs": "H5375"
        },
        {
          "id": "שאי",
          "sbl": "'e.Lav",
          "gloss": "to him",
          "lemma_strongs": "H0413",
          "suffix_strongs": "H9033"
        },
        {
          "id": "אליו",
          "sbl": "ka.Pa.yikh",
          "gloss": "your hands",
          "lemma_strongs": "H3709",
          "suffix_strongs": "H9022"
        },
        {
          "id": "כפיך",
          "sbl": "'al-",
          "gloss": "on",
          "lemma_strongs": "H5921"
        },
        {
          "id": "על",
          "sbl": "ne.fesh",
          "gloss": "[the] life",
          "lemma_strongs": "H5315"
        },
        {
          "id": "נפש",
          "sbl": "o.la.La.yikh",
          "gloss": "your children",
          "lemma_strongs": "H5768",
          "suffix_strongs": "H9022"
        },
        {
          "id": "עולליך",
          "sbl": "ha.'a.tu.Fim",
          "gloss": "the ones enfeebled",
          "prefix_strongs": "H9009",
          "lemma_strongs": "H5848"
        },
        {
          "id": "העטופים",
          "sbl": "be.ra.'Av",
          "gloss": "by hunger",
          "prefix_strongs": "H9003",
          "lemma_strongs": "H7458"
        },
        {
          "id": "ברעב",
          "sbl": "be.Rosh",
          "gloss": "at [the] head of",
          "prefix_strongs": "H9003",
          "lemma_strongs": "H7218"
        },
        {
          "id": "בראש",
          "sbl": "kol-",
          "gloss": "all",
          "lemma_strongs": "H3605"
        },
        {
          "id": "כל",
          "sbl": "chu.Tzot",
          "gloss": "[the] streets",
          "lemma_strongs": "H2351"
        },
        {
          "id": "חוצות",
          "sbl": "chûwts",
          "gloss": "separate by a wall",
          "lemma_strongs": null
        }
      ],
      "insights": []
    },
    {
      "verse": 20,
      "words": [
        {
          "id": "ראה",
          "sbl": "re.'Eh",
          "gloss": "see",
          "lemma_strongs": "H7200"
        },
        {
          "id": "יהוה",
          "sbl": "Yah.weh",
          "gloss": "O Yahweh",
          "lemma_strongs": "H3068"
        },
        {
          "id": "והביטה",
          "sbl": "ve.ha.Bi.tah",
          "gloss": "and look !",
          "prefix_strongs": "H9002",
          "lemma_strongs": "H5027",
          "suffix_strongs": "H9012"
        },
        {
          "id": "למי",
          "sbl": "le.Mi",
          "gloss": "to whom?",
          "prefix_strongs": "H9005",
          "lemma_strongs": "H4310"
        },
        {
          "id": "עוללת",
          "sbl": "o.Lal.ta",
          "gloss": "have you dealt severely",
          "lemma_strongs": "H5953"
        },
        {
          "id": "כה",
          "sbl": "Koh",
          "gloss": "thus",
          "lemma_strongs": "H3541"
        },
        {
          "id": "אם",
          "sbl": "'im-",
          "gloss": "[if]?",
          "lemma_strongs": "H0518"
        },
        {
          "id": "תאכלנה",
          "sbl": "to.Khal.nah",
          "gloss": "will eat(f)",
          "lemma_strongs": "H0398"
        },
        {
          "id": "נשים",
          "sbl": "na.Shim",
          "gloss": "women",
          "lemma_strongs": "H0802"
        },
        {
          "id": "פרים",
          "sbl": "pir.Yam",
          "gloss": "their descendant[s]",
          "lemma_strongs": "H6529",
          "suffix_strongs": "H9028"
        },
        {
          "id": "עללי",
          "sbl": "'o.la.Lei",
          "gloss": "children of",
          "lemma_strongs": "H5768"
        },
        {
          "id": "טפחים",
          "sbl": "ti.pu.Chim",
          "gloss": "health[s]",
          "lemma_strongs": "H2949"
        },
        {
          "id": "אם",
          "sbl": "'im-",
          "gloss": "or?",
          "lemma_strongs": "H0518"
        },
        {
          "id": "יהרג",
          "sbl": "ye.ha.Reg",
          "gloss": "will be killed(m)",
          "lemma_strongs": "H2026"
        },
        {
          "id": "במקדש",
          "sbl": "be.mik.Dash",
          "gloss": "in [the] sanctuary of",
          "prefix_strongs": "H9003",
          "lemma_strongs": "H4720"
        },
        {
          "id": "אדני",
          "sbl": "'a.do.Nai",
          "gloss": "[the] Lord",
          "lemma_strongs": "H0136"
        },
        {
          "id": "כהן",
          "sbl": "ko.Hen",
          "gloss": "priest",
          "lemma_strongs": "H3548"
        },
        {
          "id": "ונביא",
          "sbl": "ve.na.Vi'",
          "gloss": "and prophet",
          "prefix_strongs": "H9002",
          "lemma_strongs": "H5030"
        }
      ],
      "insights": []
    },
    {
      "verse": 21,
      "words": [
        {
          "id": "שכבו",
          "sbl": "sha.khe.Vu",
          "gloss": "have lain down",
          "lemma_strongs": "H7901"
        },
        {
          "id": "לארץ",
          "sbl": "la.'A.retz",
          "gloss": "to the ground",
          "prefix_strongs": "H9005",
          "lemma_strongs": "H0776"
        },
        {
          "id": "חוצות",
          "sbl": "chu.tzOt",
          "gloss": "streets",
          "lemma_strongs": "H2351"
        },
        {
          "id": "נער",
          "sbl": "Na.'ar",
          "gloss": "youth",
          "lemma_strongs": "H5288"
        },
        {
          "id": "וזקן",
          "sbl": "ve.za.Ken",
          "gloss": "and old [person]",
          "prefix_strongs": "H9002",
          "lemma_strongs": "H2205"
        },
        {
          "id": "בתולתי",
          "sbl": "be.tu.lo.Tai",
          "gloss": "young women my",
          "lemma_strongs": "H1330",
          "suffix_strongs": "H9020"
        },
        {
          "id": "ובחורי",
          "sbl": "u.va.chu.Rai",
          "gloss": "and young men my",
          "prefix_strongs": "H9002",
          "lemma_strongs": "H0970",
          "suffix_strongs": "H9020"
        },
        {
          "id": "נפלו",
          "sbl": "na.fe.Lu",
          "gloss": "have fallen",
          "lemma_strongs": "H5307"
        },
        {
          "id": "בחרב",
          "sbl": "ve.Cha.rev",
          "gloss": "by the sword",
          "prefix_strongs": "H9003",
          "lemma_strongs": "H2719"
        },
        {
          "id": "הרגת",
          "sbl": "ha.Rag.ta",
          "gloss": "you have killed",
          "lemma_strongs": "H2026"
        },
        {
          "id": "ביום",
          "sbl": "be.Yom",
          "gloss": "in [the] day of",
          "prefix_strongs": "H9003",
          "lemma_strongs": "H3117"
        },
        {
          "id": "אפך",
          "sbl": "'a.Pe.kha",
          "gloss": "your anger",
          "lemma_strongs": "H0639",
          "suffix_strongs": "H9021"
        },
        {
          "id": "טבחת",
          "sbl": "ta.Vach.ta",
          "gloss": "you have slaughtered",
          "lemma_strongs": "H2873"
        },
        {
          "id": "לא",
          "sbl": "lo'",
          "gloss": "not",
          "lemma_strongs": "H3808"
        },
        {
          "id": "חמלת",
          "sbl": "cha.Mal.ta",
          "gloss": "you have spared",
          "lemma_strongs": "H2550"
        }
      ],
      "insights": []
    },
    {
      "verse": 22,
      "words": [
        {
          "id": "תקרא",
          "sbl": "tik.Ra'",
          "gloss": "you have summoned",
          "lemma_strongs": "H7121"
        },
        {
          "id": "כיום",
          "sbl": "khe.Yom",
          "gloss": "like [the] day of",
          "prefix_strongs": "H9004",
          "lemma_strongs": "H3117"
        },
        {
          "id": "מועד",
          "sbl": "mo.'Ed",
          "gloss": "an appointed feast",
          "lemma_strongs": "H4150"
        },
        {
          "id": "מגורי",
          "sbl": "me.gu.Rai",
          "gloss": "terrors my",
          "lemma_strongs": "H4032",
          "suffix_strongs": "H9020"
        },
        {
          "id": "מסביב",
          "sbl": "mi.sa.Viv",
          "gloss": "from round about",
          "prefix_strongs": "H9006",
          "lemma_strongs": "H5439"
        },
        {
          "id": "ולא",
          "sbl": "ve.Lo'",
          "gloss": "and not",
          "prefix_strongs": "H9002",
          "lemma_strongs": "H3808"
        },
        {
          "id": "היה",
          "sbl": "ha.Yah",
          "gloss": "was(m)",
          "lemma_strongs": "H1961"
        },
        {
          "id": "ביום",
          "sbl": "be.Yom",
          "gloss": "in [the] day of",
          "prefix_strongs": "H9003",
          "lemma_strongs": "H3117"
        },
        {
          "id": "אף",
          "sbl": "'af-",
          "gloss": "[the] anger of",
          "lemma_strongs": "H0639"
        },
        {
          "id": "יהוה",
          "sbl": "Yah.weh",
          "gloss": "Yahweh",
          "lemma_strongs": "H3068"
        },
        {
          "id": "פליט",
          "sbl": "pa.Lit",
          "gloss": "an escapee",
          "lemma_strongs": "H6412"
        },
        {
          "id": "ושריד",
          "sbl": "ve.sa.Rid",
          "gloss": "and a survivor",
          "prefix_strongs": "H9002",
          "lemma_strongs": "H8300"
        },
        {
          "id": "אשר",
          "sbl": "'a.Sher-",
          "gloss": "[those] whom",
          "lemma_strongs": "H0834"
        },
        {
          "id": "טפחתי",
          "sbl": "ti.Pach.ti",
          "gloss": "I had given birth",
          "lemma_strongs": "H2946"
        },
        {
          "id": "ורביתי",
          "sbl": "ve.ri.Bi.ti",
          "gloss": "and I had reared",
          "prefix_strongs": "H9002",
          "lemma_strongs": "H7235"
        },
        {
          "id": "איבי",
          "sbl": "'o.ye.Vi",
          "gloss": "enemy my",
          "lemma_strongs": "H0341",
          "suffix_strongs": "H9020"
        },
        {
          "id": "כלם",
          "sbl": "khi.Lam",
          "gloss": "has made an end of them(m)",
          "lemma_strongs": "H3615",
          "suffix_strongs": "H9038"
        }
      ],
      "insights": []
    }
  ]
}