{
  "book": "psalms",
  "chapter": 6,
  "stage_index": 484,
  "verses": [
    {
      "verse": 1,
      "words": [
        {
          "id": "למנצח",
          "sbl": "Yah.weh",
          "gloss": "O Yahweh",
          "lemma_strongs": "H3068"
        },
        {
          "id": "בנגינות",
          "sbl": "'al-",
          "gloss": "may not",
          "lemma_strongs": "H0408"
        },
        {
          "id": "על",
          "sbl": "be.'a.pe.Kha",
          "gloss": "your in anger",
          "prefix_strongs": "H9003",
          "lemma_strongs": "H0639",
          "suffix_strongs": "H9021"
        },
        {
          "id": "השמינית",
          "sbl": "to.khi.Che.ni",
          "gloss": "you rebuke me",
          "lemma_strongs": "H3198",
          "suffix_strongs": "H9030"
        },
        {
          "id": "מזמור",
          "sbl": "ve.'al-",
          "gloss": "and may not",
          "prefix_strongs": "H9002",
          "lemma_strongs": "H0408"
        },
        {
          "id": "לדוד",
          "sbl": "ba.cha.ma.te.Kha",
          "gloss": "your in wrath",
          "prefix_strongs": "H9003",
          "lemma_strongs": "H2534",
          "suffix_strongs": "H9021"
        }
      ],
      "insights": []
    },
    {
      "verse": 2,
      "words": [
        {
          "id": "יהוה",
          "sbl": "cho.ne.ni",
          "gloss": "show favor to me",
          "lemma_strongs": "H2603",
          "suffix_strongs": "H9030"
        },
        {
          "id": "אל",
          "sbl": "Yah.weh",
          "gloss": "O Yahweh",
          "lemma_strongs": "H3068"
        },
        {
          "id": "באפך",
          "sbl": "ki",
          "gloss": "for",
          "lemma_strongs": "H3588"
        },
        {
          "id": "תוכיחני",
          "sbl": "'um.Lal",
          "gloss": "[am] frail",
          "lemma_strongs": "H0536"
        },
        {
          "id": "ואל",
          "sbl": "'A.ni",
          "gloss": "I",
          "lemma_strongs": "H0589"
        },
        {
          "id": "בחמתך",
          "sbl": "re.fa.'E.ni",
          "gloss": "heal me",
          "lemma_strongs": "H7495",
          "suffix_strongs": "H9030"
        },
        {
          "id": "תיסרני",
          "sbl": "Yah.weh",
          "gloss": "O Yahweh",
          "lemma_strongs": "H3068"
        }
      ],
      "insights": []
    },
    {
      "verse": 3,
      "words": [
        {
          "id": "חנני",
          "sbl": "Ve.naf.shi",
          "gloss": "and self my",
          "prefix_strongs": "H9002",
          "lemma_strongs": "H5315",
          "suffix_strongs": "H9020"
        },
        {
          "id": "יהוה",
          "sbl": "niv.ha.Lah",
          "gloss": "it is disturbed",
          "lemma_strongs": "H0926"
        },
        {
          "id": "כי",
          "sbl": "me.'Od",
          "gloss": "exceedingly",
          "lemma_strongs": "H3966"
        },
        {
          "id": "אמלל",
          "sbl": "ve.'at",
          "gloss": "and you",
          "prefix_strongs": "H9002",
          "lemma_strongs": "H0859"
        },
        {
          "id": "אני",
          "sbl": "Yah.weh",
          "gloss": "O Yahweh",
          "lemma_strongs": "H3068"
        },
        {
          "id": "רפאני",
          "sbl": "'ad-",
          "gloss": "until",
          "lemma_strongs": "H5704"
        },
        {
          "id": "יהוה",
          "sbl": "ma.Tai",
          "gloss": "when?",
          "lemma_strongs": "H4970"
        },
        {
          "id": "כי",
          "sbl": "kîy",
          "gloss": "relative conjunction",
          "lemma_strongs": null
        },
        {
          "id": "נבהלו",
          "sbl": "bâhal",
          "gloss": "tremble",
          "lemma_strongs": null
        },
        {
          "id": "עצמי",
          "sbl": "ʻetsem",
          "gloss": "bone my",
          "lemma_strongs": null
        }
      ],
      "insights": []
    },
    {
      "verse": 4,
      "words": [
        {
          "id": "ונפשי",
          "sbl": "shu.Vah",
          "gloss": "return !",
          "lemma_strongs": "H7725",
          "suffix_strongs": "H9012"
        },
        {
          "id": "נבהלה",
          "sbl": "Yah.weh",
          "gloss": "O Yahweh(f)",
          "lemma_strongs": "H3068"
        },
        {
          "id": "מאד",
          "sbl": "cha.le.Tzah",
          "gloss": "rescue !",
          "lemma_strongs": "H2502",
          "suffix_strongs": "H9012"
        },
        {
          "id": "ואת",
          "sbl": "naf.Shi",
          "gloss": "life my",
          "lemma_strongs": "H5315",
          "suffix_strongs": "H9020"
        },
        {
          "id": "ואתה",
          "sbl": "ho.shi.'E.ni",
          "gloss": "save me",
          "lemma_strongs": "H3467",
          "suffix_strongs": "H9030"
        },
        {
          "id": "יהוה",
          "sbl": "le.Ma.'an",
          "gloss": "on account of",
          "lemma_strongs": "H4616"
        },
        {
          "id": "עד",
          "sbl": "chas.De.kha",
          "gloss": "your covenant loyalty",
          "lemma_strongs": "H2617",
          "suffix_strongs": "H9021"
        },
        {
          "id": "מתי",
          "sbl": "math",
          "gloss": "adult",
          "lemma_strongs": null
        }
      ],
      "insights": []
    },
    {
      "verse": 5,
      "words": [
        {
          "id": "שובה",
          "sbl": "ki",
          "gloss": "for",
          "lemma_strongs": "H3588"
        },
        {
          "id": "יהוה",
          "sbl": "'ein",
          "gloss": "there not",
          "lemma_strongs": "H0369"
        },
        {
          "id": "חלצה",
          "sbl": "ba.Ma.vet",
          "gloss": "in [the] death",
          "prefix_strongs": "H9003",
          "lemma_strongs": "H4194"
        },
        {
          "id": "נפשי",
          "sbl": "zikh.Re.kha",
          "gloss": "[is] remembrance of you",
          "lemma_strongs": "H2143",
          "suffix_strongs": "H9021"
        },
        {
          "id": "הושיעני",
          "sbl": "bish.'ol",
          "gloss": "in Sheol",
          "prefix_strongs": "H9003",
          "lemma_strongs": "H7585"
        },
        {
          "id": "למען",
          "sbl": "mi",
          "gloss": "who?",
          "lemma_strongs": "H4310"
        },
        {
          "id": "חסדך",
          "sbl": "yo.deh-",
          "gloss": "will he give thanks",
          "lemma_strongs": "H3034"
        }
      ],
      "insights": []
    },
    {
      "verse": 6,
      "words": [
        {
          "id": "כי",
          "sbl": "ya.Ga'.ti",
          "gloss": "I have become weary",
          "lemma_strongs": "H3021"
        },
        {
          "id": "אין",
          "sbl": "be.'an.cha.Ti",
          "gloss": "by groaning my",
          "prefix_strongs": "H9003",
          "lemma_strongs": "H0585",
          "suffix_strongs": "H9020"
        },
        {
          "id": "במות",
          "sbl": "'as.Cheh",
          "gloss": "I make swim",
          "lemma_strongs": "H7811"
        },
        {
          "id": "זכרך",
          "sbl": "ve.khol-",
          "gloss": "in every",
          "prefix_strongs": "H9003",
          "lemma_strongs": "H3605"
        },
        {
          "id": "בשאול",
          "sbl": "Lay.lah",
          "gloss": "night",
          "lemma_strongs": "H3915"
        },
        {
          "id": "מי",
          "sbl": "mi.ta.Ti",
          "gloss": "bed my",
          "lemma_strongs": "H4296",
          "suffix_strongs": "H9020"
        },
        {
          "id": "יודה",
          "sbl": "be.dim.'a.Ti",
          "gloss": "with tear[s] my(m)",
          "prefix_strongs": "H9003",
          "lemma_strongs": "H1832",
          "suffix_strongs": "H9020"
        },
        {
          "id": "לך",
          "sbl": "'ar.Si",
          "gloss": "couch my",
          "lemma_strongs": "H6210",
          "suffix_strongs": "H9020"
        }
      ],
      "insights": []
    },
    {
      "verse": 7,
      "words": [
        {
          "id": "יגעתי",
          "sbl": "'a.she.Shah",
          "gloss": "has wasted away",
          "lemma_strongs": "H6244"
        },
        {
          "id": "באנחתי",
          "sbl": "mi.Ka.'as",
          "gloss": "from grief",
          "prefix_strongs": "H9006",
          "lemma_strongs": "H3708"
        },
        {
          "id": "אשחה",
          "sbl": "'ei.Ni",
          "gloss": "eye my",
          "lemma_strongs": "H5869",
          "suffix_strongs": "H9020"
        },
        {
          "id": "בכל",
          "sbl": "'a.te.Kah",
          "gloss": "it has grown weak",
          "lemma_strongs": "H6275"
        },
        {
          "id": "לילה",
          "sbl": "be.khol",
          "gloss": "with all",
          "prefix_strongs": "H9003",
          "lemma_strongs": "H3605"
        },
        {
          "id": "מטתי",
          "sbl": "tzo.Rai",
          "gloss": "opposers my",
          "lemma_strongs": "H6887",
          "suffix_strongs": "H9030"
        },
        {
          "id": "בדמעתי",
          "sbl": "dimʻâh",
          "gloss": "in weeping my",
          "lemma_strongs": null
        },
        {
          "id": "ערשי",
          "sbl": "ʻeres",
          "gloss": "couch my",
          "lemma_strongs": null
        },
        {
          "id": "אמסה",
          "sbl": "mâçâh",
          "gloss": "dissolve",
          "lemma_strongs": null
        }
      ],
      "insights": []
    },
    {
      "verse": 8,
      "words": [
        {
          "id": "עששה",
          "sbl": "Su.ru",
          "gloss": "turn away(f)",
          "lemma_strongs": "H5493"
        },
        {
          "id": "מכעס",
          "sbl": "Mi.me.ni",
          "gloss": "from me",
          "lemma_strongs": "H4480",
          "suffix_strongs": "H9030"
        },
        {
          "id": "עיני",
          "sbl": "kol-",
          "gloss": "O all",
          "lemma_strongs": "H3605"
        },
        {
          "id": "עתקה",
          "sbl": "Po.'a.lei",
          "gloss": "[those who] do(f)",
          "lemma_strongs": "H6466"
        },
        {
          "id": "בכל",
          "sbl": "'A.ven",
          "gloss": "[of] wickedness",
          "lemma_strongs": "H0205"
        },
        {
          "id": "צוררי",
          "sbl": "ki-",
          "gloss": "for",
          "lemma_strongs": "H3588"
        }
      ],
      "insights": []
    },
    {
      "verse": 9,
      "words": [
        {
          "id": "סורו",
          "sbl": "sha.Ma'",
          "gloss": "has heard",
          "lemma_strongs": "H8085"
        },
        {
          "id": "ממני",
          "sbl": "Yah.weh",
          "gloss": "Yahweh",
          "lemma_strongs": "H3068"
        },
        {
          "id": "כל",
          "sbl": "te.chi.na.Ti",
          "gloss": "supplication my",
          "lemma_strongs": "H8467",
          "suffix_strongs": "H9020"
        },
        {
          "id": "פעלי",
          "sbl": "Yah.weh",
          "gloss": "Yahweh",
          "lemma_strongs": "H3068"
        },
        {
          "id": "און",
          "sbl": "te.fi.la.Ti",
          "gloss": "prayer my",
          "lemma_strongs": "H8605",
          "suffix_strongs": "H9020"
        },
        {
          "id": "כי",
          "sbl": "yi.Kach",
          "gloss": "he will accept",
          "lemma_strongs": "H3947"
        },
        {
          "id": "שמע",
          "sbl": "Shemaʻ",
          "gloss": "Shema(m)",
          "lemma_strongs": null
        },
        {
          "id": "יהוה",
          "sbl": "Yᵉhôvâh",
          "gloss": "Existent",
          "lemma_strongs": null
        },
        {
          "id": "קול",
          "sbl": "qôwl",
          "gloss": "voice",
          "lemma_strongs": null
        },
        {
          "id": "בכיי",
          "sbl": "Bᵉkîy",
          "gloss": "weeping my",
          "lemma_strongs": null
        }
      ],
      "insights": []
    },
    {
      "verse": 10,
      "words": [
        {
          "id": "שמע",
          "sbl": "ye.Vo.shu",
          "gloss": "may be ashamed(m)",
          "lemma_strongs": "H0954"
        },
        {
          "id": "יהוה",
          "sbl": "ve.yi.ba.ha.Lu",
          "gloss": "and they may be disturbed",
          "prefix_strongs": "H9002",
          "lemma_strongs": "H0926"
        },
        {
          "id": "תחנתי",
          "sbl": "Me.'od",
          "gloss": "exceedingly",
          "lemma_strongs": "H3966"
        },
        {
          "id": "יהוה",
          "sbl": "kol-",
          "gloss": "all",
          "lemma_strongs": "H3605"
        },
        {
          "id": "תפלתי",
          "sbl": "'o.ye.Vai",
          "gloss": "enemies my",
          "lemma_strongs": "H0341",
          "suffix_strongs": "H9020"
        },
        {
          "id": "יקח",
          "sbl": "ya.Shu.vu",
          "gloss": "will turn back(m)",
          "lemma_strongs": "H7725"
        }
      ],
      "insights": []
    },
    {
      "verse": 11,
      "words": [
        {
          "id": "יבשו",
          "sbl": "yâbêsh",
          "gloss": "be ashamed(m)",
          "lemma_strongs": null
        },
        {
          "id": "ויבהלו",
          "sbl": "bâhal",
          "gloss": "and tremble(m)",
          "lemma_strongs": null
        },
        {
          "id": "מאד",
          "sbl": "mᵉʼôd",
          "gloss": "vehemence",
          "lemma_strongs": null
        },
        {
          "id": "כל",
          "sbl": "kôl",
          "gloss": "whole",
          "lemma_strongs": null
        },
        {
          "id": "איבי",
          "sbl": "ʼôyêb",
          "gloss": "hating my",
          "lemma_strongs": null
        },
        {
          "id": "ישבו",
          "sbl": "yâshab",
          "gloss": "sit(m)",
          "lemma_strongs": null
        },
        {
          "id": "יבשו",
          "sbl": "yâbêsh",
          "gloss": "be ashamed(m)",
          "lemma_strongs": null
        },
        {
          "id": "רגע",
          "sbl": "regaʻ",
          "gloss": "wink",
          "lemma_strongs": null
        }
      ],
      "insights": []
    }
  ]
}